Workbook

Sheet 支払い明細
A1: 銀行振込 支払い表 | D1: 送金日 | E1: 46042 | G1: 四国銀行 | H1: 青即引き・緑伝票引き
B2: 送り先 | C2: 請求額 | D2: 打込金額 | E2: 振込金額 | F2: 送料相手 | G2: 値引 | H2: 早払い | I2: 相殺 | J2: 備考
A3: 21 | B3: イトマン ㈱ | C3: 559416 | D3: =IF(C3="","",C3-G3-H3-I3) -> 559416 | E3: =IF(C3="","",D3-F3) -> 558646 | F3: =IF(D3="","",IF(D3=0,"",IF(D3<30000,605,IF(D3>=30000,770)))) -> 770
A4: 22 | B4: 泉 製紙 ㈱ | C4: 3572250 | D4: =IF(C4="","",C4-G4-H4-I4) -> 3518667 | E4: =IF(C4="","",D4-F4) -> 3517897 | F4: =IF(D4="","",IF(D4=0,"",IF(D4<30000,605,IF(D4>=30000,770)))) -> 770 | H4: =L4 -> 53583 | K4: =SUM(D4:D5) -> 3518667 | L4: =INT(C4*0.015) -> 53583
A5: 22 | B5: 泉製紙 第２事業部 | D5: =IF(C5="","",C5-G5-H5-I5) | E5: =IF(C5="","",D5-F5) | H5: =L5 -> 0 | L5: =INT(C5*0.015) -> 0
A6: 22 | B6: 泉製紙 第３事業部 | D6: =IF(C6="","",C6-G6-H6-I6) | E6: =IF(C6="","",D6-F6) | F6: =IF(D6="","",IF(D6=0,"",IF(D6<30000,605,IF(D6>=30000,770)))) | H6: =L6 -> 0 | J6: =SUM(C4:C6) -> 3572250 | K6: =SUM(E4:E6) -> 3517897 | L6: =INT(C6*0.015) -> 0 | M6: =SUM(L4:L6) -> 53583
A7: 95 | B7: オルディ 株式会社 | C7: 447755 | D7: =IF(C7="","",C7-G7-H7-I7) -> 447755 | E7: =IF(C7="","",D7-F7) -> 446985 | F7: =IF(D7="","",IF(D7=0,"",IF(D7<30000,605,IF(D7>=30000,770)))) -> 770
A8: 191 | B8: 木野川紙業 株式会社 | C8: 47905 | D8: =IF(C8="","",C8-G8-H8-I8) -> 47905 | E8: =IF(C8="","",D8-F8) -> 47575 | F8: =IF(D8="","",IF(D8=0,"",IF(D8<30000,110,IF(D8>=30000,330)))) -> 330 | J8: 四国大竹
A9: 210 | B9: ケイティケイ ㈱ | C9: 209301 | D9: =IF(C9="","",C9-G9-H9-I9) -> 209301 | E9: =IF(C9="","",D9-F9) -> 208531 | F9: =IF(D9="","",IF(D9=0,"",IF(D9<30000,605,IF(D9>=30000,770)))) -> 770
A10: 233 | B10: ㈱ 尚美堂 | C10: 503986 | D10: =IF(C10="","",C10-G10-H10-I10) -> 503986 | E10: =IF(C10="","",D10-F10) -> 503216 | F10: =IF(D10="","",IF(D10=0,"",IF(D10<30000,605,IF(D10>=30000,770)))) -> 770
A11: 241 | B11: シーバイエス ㈱ | C11: 568370 | D11: =IF(C11="","",C11-G11-H11-I11) -> 568370 | E11: =IF(C11="","",D11-F11) -> 567600 | F11: =IF(D11="","",IF(D11=0,"",IF(D11<30000,605,IF(D11>=30000,770)))) -> 770
A12: 251 | B12: ㈱ スズカ未来 | C12: 158928 | D12: =IF(C12="","",C12-G12-H12-I12) -> 158928 | E12: =IF(C12="","",D12-F12) -> 158158 | F12: =IF(D12="","",IF(D12=0,"",IF(D12<30000,605,IF(D12>=30000,770)))) -> 770
A13: 323 | B13: 中国鉄管継手㈱ | D13: =IF(C13="","",C13-G13-H13-I13) | E13: =IF(C13="","",D13-F13) | F13: =IF(D13="","",IF(D13=0,"",IF(D13<30000,605,IF(D13>=30000,770))))
A14: 371 | B14: ツバメ工業 | D14: =IF(C14="","",C14-G14-H14-I14) | E14: =IF(C14="","",D14-F14) | F14: =IF(D14="","",IF(D14=0,"",IF(D14<30000,605,IF(D14>=30000,770))))
A15: 411 | B15: ㈱ 奈良半商店 | D15: =IF(C15="","",C15-G15-H15-I15) | E15: =IF(C15="","",D15-F15) | F15: =IF(D15="","",IF(D15=0,"",IF(D15<30000,605,IF(D15>=30000,770))))
A16: 401 | B16: 中川製袋化工 ㈱ | C16: 796810 | D16: =IF(C16="","",C16-G16-H16-I16) -> 794420 | E16: =IF(C16="","",D16-F16) -> 794090 | F16: =IF(D16="","",IF(D16=0,"",IF(D16<30000,110,IF(D16>=30000,330)))) -> 330 | H16: =L16 -> 2390 | L16: =INT(C16*0.003) -> 2390 | M16: R6.10.20〆より0.3%引き
A17: 525 | B17: 広島共和物産㈱ | C17: 513289 | D17: =IF(C17="","",C17-G17-H17-I17) -> 513289 | E17: =IF(C17="","",D17-F17) -> 512519 | F17: =IF(D17="","",IF(D17=0,"",IF(D17<30000,605,IF(D17>=30000,770)))) -> 770
A18: 541 | B18: 福助工業㈱ | C18: 1621191 | D18: =IF(C18="","",C18-G18-H18-I18) -> 1616328 | E18: =IF(C18="","",D18-F18) -> 1615558 | F18: =IF(D18="","",IF(D18=0,"",IF(D18<30000,605,IF(D18>=30000,770)))) -> 770 | H18: =L18 -> 4863 | L18: =INT(C18*0.003) -> 4863 | M18: R6.3.20〆より0.3%引き
A19: 711 | B19: ㈱ やしき | D19: =IF(C19="","",C19-G19-H19-I19) | E19: =IF(C19="","",D19-F19) | F19: =IF(D19="","",IF(D19=0,"",IF(D19<30000,605,IF(D19>=30000,770))))
A20: 751 | B20: ユニ・チャーム ㈱ | C20: 1429592 | D20: =IF(C20="","",C20-G20-H20-I20) -> 1429592 | E20: =IF(C20="","",D20-F20) -> 1428822 | F20: =IF(D20="","",IF(D20=0,"",IF(D20<30000,605,IF(D20>=30000,770)))) -> 770
A21: 1002 | B21: 旭創業 ㈱ | C21: 395263 | D21: =IF(C21="","",C21-G21-H21-I21) -> 395263 | E21: =IF(C21="","",D21-F21) -> 394493 | F21: =IF(D21="","",IF(D21=0,"",IF(D21<30000,605,IF(D21>=30000,770)))) -> 770
A22: 1003 | B22: ㈱ アルファ | D22: =IF(C22="","",C22-G22-H22-I22) | E22: =IF(C22="","",D22-F22) | F22: =IF(D22="","",IF(D22=0,"",IF(D22<30000,605,IF(D22>=30000,770))))
A23: 1080 | B23: ㈱ 大阪包装社 | D23: =IF(C23="","",C23-G23-H23-I23) | E23: =IF(C23="","",D23-F23) | F23: =IF(D23="","",IF(D23=0,"",IF(D23<30000,605,IF(D23>=30000,770))))
A24: 1102 | B24: カミイソ産商 ㈱ | C24: 18700 | D24: =IF(C24="","",C24-G24-H24-I24) -> 18700 | E24: =IF(C24="","",D24-F24) -> 18095 | F24: =IF(D24="","",IF(D24=0,"",IF(D24<30000,605,IF(D24>=30000,770)))) -> 605
A25: 1120 | B25: 木村アルミ箔 ㈱ | D25: =IF(C25="","",C25-G25-H25-I25) | E25: =IF(C25="","",D25-F25) | F25: =IF(D25="","",IF(D25=0,"",IF(D25<30000,605,IF(D25>=30000,770))))
A26: 1201 | B26: 酒井美化工業 ㈱ | D26: =IF(C26="","",C26-G26-H26-I26) | E26: =IF(C26="","",D26-F26) | F26: =IF(D26="","",IF(D26=0,"",IF(D26<30000,605,IF(D26>=30000,770))))
A27: 1203 | B27: ㈱ ササガワ | D27: =IF(C27="","",C27-G27-H27-I27) | E27: =IF(C27="","",D27-F27) | F27: =IF(D27="","",IF(D27=0,"",IF(D27<30000,605,IF(D27>=30000,770))))
A28: 1221 | B28: ㈱ 四国フソウ | D28: =IF(C28="","",C28-G28-H28-I28) | E28: =IF(C28="","",D28-F28) | F28: =IF(D28="","",IF(D28=0,"",IF(D28<30000,605,IF(D28>=30000,770))))
A29: 1222 | B29: 信和 ㈱ | D29: =IF(C29="","",C29-G29-H29-I29) | E29: =IF(C29="","",D29-F29) | F29: =IF(D29="","",IF(D29=0,"",IF(D29<30000,605,IF(D29>=30000,770))))
A30: 1260 | B30: ㈱ セイコー | D30: =IF(C30="","",C30-G30-H30-I30) | E30: =IF(C30="","",D30-F30) | F30: =IF(D30="","",IF(D30=0,"",IF(D30<30000,605,IF(D30>=30000,770)))) | H30: =K30 | K30: =IF(C30="","",INT(C30*0.02))
A31: 1301 | B31: ㈱ 太幸 | D31: =IF(C31="","",C31-G31-H31-I31) | E31: =IF(C31="","",D31-F31) | F31: =IF(D31="","",IF(D31=0,"",IF(D31<30000,605,IF(D31>=30000,770))))
A32: 1302 | B32: 大黒工業㈱ | C32: 67650 | D32: =IF(C32="","",C32-G32-H32-I32) -> 67650 | E32: =IF(C32="","",D32-F32) -> 66880 | F32: =IF(D32="","",IF(D32=0,"",IF(D32<30000,605,IF(D32>=30000,770)))) -> 770
A33: 1303 | B33: ㈱ パックタケヤマ | C33: 74228 | D33: =IF(C33="","",C33-G33-H33-I33) -> 74228 | E33: =IF(C33="","",D33-F33) -> 73458 | F33: =IF(D33="","",IF(D33=0,"",IF(D33<30000,605,IF(D33>=30000,770)))) -> 770
A34: 1304 | B34: ㈲ タイヨー | D34: =IF(C34="","",C34-G34-H34-I34) | E34: =IF(C34="","",D34-F34) | F34: =IF(D34="","",IF(D34=0,"",IF(D34<30000,605,IF(D34>=30000,770))))
A35: 1320 | B35: ㈱ ちどり産業 | D35: =IF(C35="","",C35-G35-H35-I35) | E35: =IF(C35="","",D35-F35) | F35: =IF(D35="","",IF(D35=0,"",IF(D35<30000,605,IF(D35>=30000,770))))
A36: 1321 | B36: シーピー化成 ㈱ | D36: =IF(C36="","",C36-G36-H36-I36) | E36: =IF(C36="","",D36-F36) | F36: =IF(D36="","",IF(D36=0,"",IF(D36<30000,605,IF(D36>=30000,770))))
A37: 1322 | B37: カネカ食品販売 ㈱ | D37: =IF(C37="","",C37-G37-H37-I37) | E37: =IF(C37="","",D37-F37) | F37: =IF(D37="","",IF(D37=0,"",IF(D37<30000,605,IF(D37>=30000,770))))
A38: 1325 | B38: ㈱ 中国リス食品販売 | D38: =IF(C38="","",C38-G38-H38-I38) | E38: =IF(C38="","",D38-F38) | F38: =IF(D38="","",IF(D38=0,"",IF(D38<30000,605,IF(D38>=30000,770))))
A39: 1360 | B39: 天満紙器 株式会社 | C39: 425282 | D39: =IF(C39="","",C39-G39-H39-I39) -> 425282 | E39: =IF(C39="","",D39-F39) -> 424512 | F39: =IF(D39="","",IF(D39=0,"",IF(D39<30000,605,IF(D39>=30000,770)))) -> 770
A40: 1380 | B40: 東光 株式会社 | C40: 134866 | D40: =IF(C40="","",C40-G40-H40-I40) -> 134866 | E40: =IF(C40="","",D40-F40) -> 134096 | F40: =IF(D40="","",IF(D40=0,"",IF(D40<30000,605,IF(D40>=30000,770)))) -> 770
A41: 1381 | B41: ㈲ 東予割箸 | D41: =IF(C41="","",C41-G41-H41-I41) | E41: =IF(C41="","",D41-F41) | F41: =IF(D41="","",IF(D41=0,"",IF(D41<30000,605,IF(D41>=30000,770))))
A42: 1382 | B42: ㈲ トックブランシュ | D42: =IF(C42="","",C42-G42-H42-I42) | E42: =IF(C42="","",D42-F42) | F42: =IF(D42="","",IF(D42=0,"",IF(D42<30000,605,IF(D42>=30000,770))))
A43: 1401 | B43: ナカパック産業 ㈱ | D43: =IF(C43="","",C43-G43-H43-I43) | E43: =IF(C43="","",D43-F43) | F43: =IF(D43="","",IF(D43=0,"",IF(D43<30000,605,IF(D43>=30000,770))))
A44: 1402 | B44: ㈱ 中村製紙所 | D44: =IF(C44="","",C44-G44-H44-I44) | E44: =IF(C44="","",D44-F44) | F44: =IF(D44="","",IF(D44=0,"",IF(D44<30000,605,IF(D44>=30000,770))))
A45: 1420 | B45: ㈱ ニューパック住友 | D45: =IF(C45="","",C45-G45-H45-I45) | E45: =IF(C45="","",D45-F45) | F45: =IF(D45="","",IF(D45=0,"",IF(D45<30000,605,IF(D45>=30000,770))))
A46: 1503 | B46: ㈱ ﾊﾗﾌﾟﾚｯｸｽ松山支店 | C46: 60500 | D46: =IF(C46="","",C46-G46-H46-I46) -> 60500 | E46: =IF(C46="","",D46-F46) -> 59730 | F46: =IF(D46="","",IF(D46=0,"",IF(D46<30000,605,IF(D46>=30000,770)))) -> 770
A47: 1510 | B47: 広川 ㈱ | D47: =IF(C47="","",C47-G47-H47-I47) | E47: =IF(C47="","",D47-F47) | F47: =IF(D47="","",IF(D47=0,"",IF(D47<30000,605,IF(D47>=30000,770))))
A48: 1540 | B48: ㈱ フォーデック | D48: =IF(C48="","",C48-G48-H48-I48) | E48: =IF(C48="","",D48-F48) | F48: =IF(D48="","",IF(D48=0,"",IF(D48<30000,605,IF(D48>=30000,770))))
A49: 1541 | B49: ㈱ 福重 | D49: =IF(C49="","",C49-G49-H49-I49) | E49: =IF(C49="","",D49-F49) | F49: =IF(D49="","",IF(D49=0,"",IF(D49<30000,605,IF(D49>=30000,770))))
A50: 1542 | B50: ㈱ プライム.ハラ | D50: =IF(C50="","",C50-G50-H50-I50) | E50: =IF(C50="","",D50-F50) | F50: =IF(D50="","",IF(D50=0,"",IF(D50<30000,605,IF(D50>=30000,770))))
A51: 1543 | B51: ㈱ 藤井包材 | D51: =IF(C51="","",C51-G51-H51-I51) | E51: =IF(C51="","",D51-F51) | F51: =IF(D51="","",IF(D51=0,"",IF(D51<30000,605,IF(D51>=30000,770))))
A52: 1560 | B52: ㈱ ベルベ | D52: =IF(C52="","",C52-G52-H52-I52) | E52: =IF(C52="","",D52-F52) | F52: =IF(D52="","",IF(D52=0,"",IF(D52<30000,605,IF(D52>=30000,770))))
A53: 1580 | B53: ホリアキ 株式会社 | C53: 109560 | D53: =IF(C53="","",C53-G53-H53-I53) -> 109560 | E53: =IF(C53="","",D53-F53) -> 108790 | F53: =IF(D53="","",IF(D53=0,"",IF(D53<30000,605,IF(D53>=30000,770)))) -> 770 | K53: =IF(C53="","",INT(C53*0.015)) -> 1643 | L53: 10万円以上 | M53: 伝票で処理
A54: 1585 | B54: 信越ファインテック ㈱ | D54: =IF(C54="","",C54-G54-H54-I54) | E54: =IF(C54="","",D54-F54) | F54: =IF(D54="","",IF(D54=0,"",IF(D54<30000,605,IF(D54>=30000,770)))) | J54: 信越ﾎﾟﾘﾏｰ㈱より事業移管 | L54: 振込口座変更あり | M54: 三菱UFJ 本店 当座 2159274
A55: 1610 | B55: ㈱ 丸三 | D55: =IF(C55="","",C55-G55-H55-I55) | E55: =IF(C55="","",D55-F55) | F55: =IF(D55="","",IF(D55=0,"",IF(D55<30000,330,IF(D55>=30000,550)))) | J55: 四国銀行
A56: 1680 | B56: 森川 ㈱ | C56: 444602 | D56: =IF(C56="","",C56-G56-H56-I56) -> 444602 | E56: =IF(C56="","",D56-F56) -> 443832 | F56: =IF(D56="","",IF(D56=0,"",IF(D56<30000,605,IF(D56>=30000,770)))) -> 770
A57: 1702 | B57: 八家化学工業 ㈱ | D57: =IF(C57="","",C57-G57-H57-I57) | E57: =IF(C57="","",D57-F57) | F57: =IF(D57="","",IF(D57=0,"",IF(D57<30000,605,IF(D57>=30000,770))))
A58: 1720 | B58: ㈱ ユタカフードパック | D58: =IF(C58="","",C58-G58-H58-I58) | E58: =IF(C58="","",D58-F58) | F58: =IF(D58="","",IF(D58=0,"",IF(D58<30000,605,IF(D58>=30000,770))))
A59: 1740 | B59: ㈱ よし与工房 | D59: =IF(C59="","",C59-G59-H59-I59) | E59: =IF(C59="","",D59-F59) | F59: =IF(D59="","",IF(D59=0,"",IF(D59<30000,605,IF(D59>=30000,770))))
B60: 本社仕入 合計 | C60: =SUM(C3:C59) -> 12159444 | D60: =SUM(D3:D59) -> 12098608 | E60: =SUM(E3:E59) -> 12083483 | F60: =SUM(F3:F59) -> 15125 | H60: =SUM(H3:H59) -> 60836 | L60: =SUM(E60:H60) -> 12159444
B61: 福山通運 | C61: 153087 | D61: =IF(C61="","",C61-G61-H61-I61) -> 153087 | E61: =IF(C61="","",D61-F61) -> 152317 | F61: =IF(D61="","",IF(D61=0,"",IF(D61<30000,605,IF(D61>=30000,770)))) -> 770 | J61: 物販部 運賃
B62: 福山通運 第３事業部 | D62: =IF(C62="","",C62-G62-H62-I62) | E62: =IF(C62="","",D62-F62) | F62: =IF(D62="","",IF(D62=0,"",IF(D62<30000,605,IF(D62>=30000,770))))
B63: サクマ運輸㈱ | C63: 203797 | D63: =IF(C63="","",C63-G63-H63-I63) -> 203797 | E63: =IF(C63="","",D63-F63) -> 203027 | F63: =IF(D63="","",IF(D63=0,"",IF(D63<30000,605,IF(D63>=30000,770)))) -> 770 | J63: 物販部 運賃
B64: ティックトランスポート㈲ | C64: 128931 | D64: =IF(C64="","",C64-G64-H64-I64) -> 128931 | E64: =IF(C64="","",D64-F64) -> 128161 | F64: =IF(D64="","",IF(D64=0,"",IF(D64<30000,605,IF(D64>=30000,770)))) -> 770 | J64: 物販部 運賃
B65: ヨハネ印刷㈱ | C65: 70400 | D65: =IF(C65="","",C65-G65-H65-I65) -> 70400 | E65: =IF(C65="","",D65-F65) -> 69630 | F65: =IF(D65="","",IF(D65=0,"",IF(D65<30000,605,IF(D65>=30000,770)))) -> 770 | J65: 物販部 仕入
B66: リコージャパン㈱ | C66: 18062 | D66: =IF(C66="","",C66-G66-H66-I66) -> 18062 | E66: =IF(C66="","",D66-F66) -> 17457 | F66: =IF(D66="","",IF(D66=0,"",IF(D66<30000,605,IF(D66>=30000,770)))) -> 605 | J66: 物販部 事務用品費
B67: 広島トヨペット㈱ | C67: 540011 | D67: =IF(C67="","",C67-G67-H67-I67) -> 540011 | E67: =IF(C67="","",D67-F67) -> 539241 | F67: =IF(D67="","",IF(D67=0,"",IF(D67<30000,605,IF(D67>=30000,770)))) -> 770 | J67: 車両費
B68: ㈱ ナカガワ | C68: 84810 | D68: =IF(C68="","",C68-G68-H68-I68) -> 84810 | E68: =IF(C68="","",D68-F68) -> 84040 | F68: =IF(D68="","",IF(D68=0,"",IF(D68<30000,605,IF(D68>=30000,770)))) -> 770 | J68: 物販部 仕入
B69: 中国エンゼル㈱ | D69: =IF(C69="","",C69-G69-H69-I69) | E69: =IF(C69="","",D69-F69) | F69: =IF(D69="","",IF(D69=0,"",IF(D69<30000,605,IF(D69>=30000,770)))) | J69: 物販部 仕入
B70: ㈱ ビバ | D70: =IF(C70="","",C70-G70-H70-I70) | E70: =IF(C70="","",D70-F70) | F70: =IF(D70="","",IF(D70=0,"",IF(D70<30000,605,IF(D70>=30000,770))))
A71: 5 | B71: アスト株式会社 | D71: =IF(C71="","",C71-G71-H71-I71) | E71: =IF(C71="","",D71-F71)
B72: その他計 | C72: =SUM(C61:C71) -> 1199098 | D72: =SUM(D61:D71) -> 1199098 | E72: =SUM(E61:E71) -> 1193873 | F72: =SUM(F61:F71) -> 5225 | G72: =SUM(G61:G70) -> 0 | H72: =SUM(H65:H71) -> 0 | I72: =SUM(I61:I70) -> 0 | L72: =SUM(E72:F72) -> 1199098
A73: 合計 | C73: =C60+C72 -> 13358542 | D73: =D60+D72 -> 13297706 | E73: =E60+E72 -> 13277356 | F73: =F60+F72 -> 20350 | G73: =G60+G72 -> 0 | H73: =H60+H72 -> 60836 | I73: =I60+I72 -> 0
B77: 20日払い振込手数料こちら持ち分 | C77: =E1 -> 46042
C78: 請求額 | D78: 打ち込み額 | E78: 振込金額
B79: ワタキューセイモア㈱ | C79: 11715 | D79: =IF(C79="","",C79-G79-H79-I79) -> 11715 | E79: =IF(C79="","",D79-F79) -> 11715 | F79: 0 | J79: 物販部 仕入 | L79: 小川商会
B80: ハウスホールドジャパン㈱ | C80: 118426 | D80: =IF(C80="","",C80-G80-H80-I80) -> 118426 | E80: =IF(C80="","",D80-F80) -> 118426 | F80: 0 | J80: 物販部 仕入 | L80: ㈱ ゴークラ
B81: 中国鉄管継手㈱ | D81: =IF(C81="","",C81-G81-H81-I81) | E81: =IF(C81="","",D81-F81) | F81: 0 | J81: 物販部 買掛金 | L81: シンワ ㈱
B82: ナカパック産業 ㈱ | C82: 17820 | D82: =IF(C82="","",C82-G82-H82-I82) -> 17820 | E82: =IF(C82="","",D82-F82) -> 17820 | F82: 0 | J82: 物販部 仕入
B83: ㈱ 太幸 | C83: 13915 | D83: =IF(C83="","",C83-G83-H83-I83) -> 13915 | E83: =IF(C83="","",D83-F83) -> 13915 | F83: 0 | J83: 物販部 仕入
B84: ㈱ ユタカフードパック | D84: =IF(C84="","",C84-G84-H84-I84) | E84: =IF(C84="","",D84-F84) | F84: 0 | J84: 物販部 仕入
B85: 廣川 ㈱ | D85: =IF(C85="","",C85-G85-H85-I85) | E85: =IF(C85="","",D85-F85) | F85: 0 | J85: 物販部 仕入 | L85: 三菱UFJ 上六支店 当座1502777
B86: ㈲ シルバー化成工業所 | D86: =IF(C86="","",C86-G86-H86-I86) | E86: =IF(C86="","",D86-F86) | F86: 0 | J86: 物販部 仕入
B87: 小計 | C87: =SUM(C79:C86) -> 161876 | D87: =SUM(D79:D86) -> 161876 | E87: =SUM(E79:E86) -> 161876
C596: 1

Sheet 中川製袋
H2: 46035
B3: 中川製袋化工 株式会社 御中
D4: 経理 御担当者 様
D5: 山 村 様 | G5: 小田光 株式会社
G6: 本社 広島県大竹市元町四丁目2-10
G7: ＴＥＬ 0827-53-2227
G8: ＦＡＸ 0827-53-2228
C10: いつもお世話になり ありがとうございます。
C11: 振り込み金額をお知らせいたします。
C12: ご確認よろしくお願い申し上げます。
D15: 2025年 12月請求書
F17: 振込み日 | G17: =支払い明細!E1 -> 46042
D19: ご請求金額 | E19: 振込手数料 | F19: 値引 | G19: お振込み金額
D20: =支払い明細!C16 -> 796810 | E20: =支払い明細!F16 -> 330 | F20: =支払い明細!L16 -> 2390 | G20: =D20-E20-F20 -> 794090
D21: =[1]支払い明細!C5 -> 0 | F21: =[1]支払い明細!L5 -> 0 | G21: =D21-E21-F21 -> 0
D22: =[1]支払い明細!C6 -> 0 | F22: =[1]支払い明細!L6 -> 0 | G22: =D22-E22-F22 -> 0
D23: =SUM(D20:D22) -> 796810 | E23: =E20 -> 330 | F23: =SUM(F20:F22) -> 2390 | G23: =INT(SUM(G20:G22)) -> 794090 | I23: =支払い明細!E16 -> 794090
F25: ※値引金額 | G25: ご請求額×0.003

Sheet 福通運賃明細
F2: =支払い明細!E1 -> 46042
A4: 福山通運㈱ 広島支店 御中 | K4: ＴＥＬ ０８２－２３２－７１４４
C5: 北山 様 | E5: 小田光 株式会社 | K5: ＦＡＸ ０８２－２９１－１２６０
E6: 本社 広島県大竹市元町四丁目2-10
F7: ＴＥＬ 0827-53-2227
F8: ＦＡＸ 0827-53-2228
B10: いつもお世話になり ありがとうございます。
B11: 貴社へ振り込みの営業所別明細を送ります。
B12: 入金処理をよろしくお願いいたします。
E16: 振込み日 | F16: =支払い明細!E1 -> 46042
B17: 貴社請求支店 | C17: 弊社営業所 | D17: 金 額 | E17: 振込料 | F17: 計 | J17: 貴社請求支店 | K17: 弊社営業所 | L17: 金 額 | M17: 振込料 | N17: 計
B18: 岩 国 | C18: 大 竹 | D18: =支払い明細!C61 -> 153087 | E18: 770 | F18: =INT(D18-E18) -> 152317 | J18: 岩 国 | K18: 広島 | L18: =支払い明細!L52 -> 0 | N18: =INT(L18-M18) -> 0
B19: 松 山 | C19: 大 竹 | F19: =INT(D19-E19) -> 0 | J19: 安佐南 | K19: 広島 | N19: =INT(L19-M19) -> 0
B20: 高 松 | C20: 大 竹 | F20: =INT(D20-E20) -> 0 | J20: 綾 部 | K20: 大竹 | L20: =支払い明細!L56 -> 0 | M20: 880 | N20: =INT(L20-M20) -> -880
B21: 振込送金額 | D21: =INT(SUM(D18:D20)) -> 153087 | E21: =SUM(E18:E20) -> 770 | F21: =SUM(F18:F20) -> 152317 | H21: =支払い明細!C61 -> 153087 | J21: 岡山東 | K21: ｻﾗﾀﾞ館 | N21: =INT(L21-M21) -> 0
J22: 徳島 | K22: 徳島 | N22: =INT(L22-M22) -> 0
J23: 松 山 | K23: 松山 | L23: =支払い明細!L57 -> 0 | N23: =INT(L23-M23) -> 0
J24: 山陰 | K24: 益田 | N24: =INT(L24-M24) -> 0
J25: 振込送金額 | L25: =INT(SUM(L18:L24)) -> 0 | M25: =INT(SUM(M18:M24)) -> 880 | N25: =INT(SUM(N18:N24)) -> -880

Sheet MF変換
A1: 取引No | B1: 取引日 | C1: 借方勘定科目 | D1: 借方補助科目 | E1: 借方部門 | F1: 借方取引先 | G1: 借方税区分 | H1: 借方インボイス | I1: 借方金額(円) | J1: 貸方勘定科目 | K1: 貸方補助科目 | L1: 貸方部門 | M1: 貸方取引先 | N1: 貸方税区分 | O1: 貸方インボイス | P1: 貸方金額(円) | Q1: 摘要 | R1: タグ | S1: メモ
B2: =支払い明細!$E$1 -> 46042 | C2: 買掛金 | D2: =IF(IFERROR(VLOOKUP(支払い明細!B3,変換MAP!A:B,2,FALSE),"")=0,"",IFERROR(VLOOKUP(支払い明細!B3,変換MAP!A:B,2,FALSE),"")) -> イトマン（株） | G2: 対象外 | I2: =支払い明細!C3 -> 559416 | J2: 資金複合 | N2: 対象外 | P2: =I2 -> 559416 | Q2: =D2 -> イトマン（株）
B3: =支払い明細!$E$1 -> 46042 | C3: 買掛金 | D3: =IF(IFERROR(VLOOKUP(支払い明細!B4,変換MAP!A:B,2,FALSE),"")=0,"",IFERROR(VLOOKUP(支払い明細!B4,変換MAP!A:B,2,FALSE),"")) -> 泉製紙（株） | G3: 対象外 | I3: =支払い明細!C4 -> 3572250 | J3: 資金複合 | N3: 対象外 | P3: =I3 -> 3572250 | Q3: =D3 -> 泉製紙（株）
B4: =支払い明細!$E$1 -> 46042 | C4: 買掛金 | D4: =IF(IFERROR(VLOOKUP(支払い明細!B5,変換MAP!A:B,2,FALSE),"")=0,"",IFERROR(VLOOKUP(支払い明細!B5,変換MAP!A:B,2,FALSE),"")) | G4: 対象外 | I4: =支払い明細!C5 -> 0 | J4: 資金複合 | N4: 対象外 | P4: =I4 -> 0 | Q4: =D4
B5: =支払い明細!$E$1 -> 46042 | C5: 買掛金 | D5: =IF(IFERROR(VLOOKUP(支払い明細!B6,変換MAP!A:B,2,FALSE),"")=0,"",IFERROR(VLOOKUP(支払い明細!B6,変換MAP!A:B,2,FALSE),"")) | G5: 対象外 | I5: =支払い明細!C6 -> 0 | J5: 資金複合 | N5: 対象外 | P5: =I5 -> 0 | Q5: =D5
B6: =支払い明細!$E$1 -> 46042 | C6: 買掛金 | D6: =IF(IFERROR(VLOOKUP(支払い明細!B7,変換MAP!A:B,2,FALSE),"")=0,"",IFERROR(VLOOKUP(支払い明細!B7,変換MAP!A:B,2,FALSE),"")) -> オルディ株式会社 | G6: 対象外 | I6: =支払い明細!C7 -> 447755 | J6: 資金複合 | N6: 対象外 | P6: =I6 -> 447755 | Q6: =D6 -> オルディ株式会社
B7: =支払い明細!$E$1 -> 46042 | C7: 買掛金 | D7: =IF(IFERROR(VLOOKUP(支払い明細!B8,変換MAP!A:B,2,FALSE),"")=0,"",IFERROR(VLOOKUP(支払い明細!B8,変換MAP!A:B,2,FALSE),"")) -> 木野川紙業（株） | G7: 対象外 | I7: =支払い明細!C8 -> 47905 | J7: 資金複合 | N7: 対象外 | P7: =I7 -> 47905 | Q7: =D7 -> 木野川紙業（株）
B8: =支払い明細!$E$1 -> 46042 | C8: 買掛金 | D8: =IF(IFERROR(VLOOKUP(支払い明細!B9,変換MAP!A:B,2,FALSE),"")=0,"",IFERROR(VLOOKUP(支払い明細!B9,変換MAP!A:B,2,FALSE),"")) -> ｋｔｋ ケイティケイ（株） | G8: 対象外 | I8: =支払い明細!C9 -> 209301 | J8: 資金複合 | N8: 対象外 | P8: =I8 -> 209301 | Q8: =D8 -> ｋｔｋ ケイティケイ（株）
B9: =支払い明細!$E$1 -> 46042 | C9: 買掛金 | D9: =IF(IFERROR(VLOOKUP(支払い明細!B10,変換MAP!A:B,2,FALSE),"")=0,"",IFERROR(VLOOKUP(支払い明細!B10,変換MAP!A:B,2,FALSE),"")) -> （株）尚美堂 | G9: 対象外 | I9: =支払い明細!C10 -> 503986 | J9: 資金複合 | N9: 対象外 | P9: =I9 -> 503986 | Q9: =D9 -> （株）尚美堂
B10: =支払い明細!$E$1 -> 46042 | C10: 買掛金 | D10: =IF(IFERROR(VLOOKUP(支払い明細!B11,変換MAP!A:B,2,FALSE),"")=0,"",IFERROR(VLOOKUP(支払い明細!B11,変換MAP!A:B,2,FALSE),"")) -> シーバイエス（株） | G10: 対象外 | I10: =支払い明細!C11 -> 568370 | J10: 資金複合 | N10: 対象外 | P10: =I10 -> 568370 | Q10: =D10 -> シーバイエス（株）
B11: =支払い明細!$E$1 -> 46042 | C11: 買掛金 | D11: =IF(IFERROR(VLOOKUP(支払い明細!B12,変換MAP!A:B,2,FALSE),"")=0,"",IFERROR(VLOOKUP(支払い明細!B12,変換MAP!A:B,2,FALSE),"")) -> （株）スズカ未来 | G11: 対象外 | I11: =支払い明細!C12 -> 158928 | J11: 資金複合 | N11: 対象外 | P11: =I11 -> 158928 | Q11: =D11 -> （株）スズカ未来
B12: =支払い明細!$E$1 -> 46042 | C12: 買掛金 | D12: =IF(IFERROR(VLOOKUP(支払い明細!B13,変換MAP!A:B,2,FALSE),"")=0,"",IFERROR(VLOOKUP(支払い明細!B13,変換MAP!A:B,2,FALSE),"")) | G12: 対象外 | I12: =支払い明細!C13 -> 0 | J12: 資金複合 | N12: 対象外 | P12: =I12 -> 0 | Q12: =D12
B13: =支払い明細!$E$1 -> 46042 | C13: 買掛金 | D13: =IF(IFERROR(VLOOKUP(支払い明細!B14,変換MAP!A:B,2,FALSE),"")=0,"",IFERROR(VLOOKUP(支払い明細!B14,変換MAP!A:B,2,FALSE),"")) | G13: 対象外 | I13: =支払い明細!C14 -> 0 | J13: 資金複合 | N13: 対象外 | P13: =I13 -> 0 | Q13: =D13
... B48: =支払い明細!$E$1 -> 46042 | C48: 買掛金 | D48: =IF(IFERROR(VLOOKUP(支払い明細!B49,変換MAP!A:B,2,FALSE),"")=0,"",IFERROR(VLOOKUP(支払い明細!B49,変換MAP!A:B,2,FALSE),"")) | G48: 対象外 | I48: =支払い明細!C49 -> 0 | J48: 資金複合 | N48: 対象外 | P48: =I48 -> 0 | Q48: =D48
B49: =支払い明細!$E$1 -> 46042 | C49: 買掛金 | D49: =IF(IFERROR(VLOOKUP(支払い明細!B50,変換MAP!A:B,2,FALSE),"")=0,"",IFERROR(VLOOKUP(支払い明細!B50,変換MAP!A:B,2,FALSE),"")) | G49: 対象外 | I49: =支払い明細!C50 -> 0 | J49: 資金複合 | N49: 対象外 | P49: =I49 -> 0
B50: =支払い明細!$E$1 -> 46042 | C50: 買掛金 | D50: =IF(IFERROR(VLOOKUP(支払い明細!B51,変換MAP!A:B,2,FALSE),"")=0,"",IFERROR(VLOOKUP(支払い明細!B51,変換MAP!A:B,2,FALSE),"")) | G50: 対象外 | I50: =支払い明細!C51 -> 0 | J50: 資金複合 | N50: 対象外 | P50: =I50 -> 0
B51: =支払い明細!$E$1 -> 46042 | C51: 買掛金 | D51: =IF(IFERROR(VLOOKUP(支払い明細!B52,変換MAP!A:B,2,FALSE),"")=0,"",IFERROR(VLOOKUP(支払い明細!B52,変換MAP!A:B,2,FALSE),"")) | G51: 対象外 | I51: =支払い明細!C52 -> 0 | J51: 資金複合 | N51: 対象外 | P51: =I51 -> 0
B52: =支払い明細!$E$1 -> 46042 | C52: 買掛金 | D52: =IF(IFERROR(VLOOKUP(支払い明細!B53,変換MAP!A:B,2,FALSE),"")=0,"",IFERROR(VLOOKUP(支払い明細!B53,変換MAP!A:B,2,FALSE),"")) -> ホリアキ（株） | G52: 対象外 | I52: =支払い明細!C53 -> 109560 | J52: 資金複合 | N52: 対象外 | P52: =I52 -> 109560 | Q52: =D52 -> ホリアキ（株）
B53: =支払い明細!$E$1 -> 46042 | C53: 買掛金 | D53: =IF(IFERROR(VLOOKUP(支払い明細!B54,変換MAP!A:B,2,FALSE),"")=0,"",IFERROR(VLOOKUP(支払い明細!B54,変換MAP!A:B,2,FALSE),"")) -> 信越ファインテック（株） | G53: 対象外 | I53: =支払い明細!C54 -> 0 | J53: 資金複合 | N53: 対象外 | P53: =I53 -> 0 | Q53: =D53 -> 信越ファインテック（株）
B54: =支払い明細!$E$1 -> 46042 | C54: 買掛金 | D54: =IF(IFERROR(VLOOKUP(支払い明細!B55,変換MAP!A:B,2,FALSE),"")=0,"",IFERROR(VLOOKUP(支払い明細!B55,変換MAP!A:B,2,FALSE),"")) -> （株）丸三 | G54: 対象外 | I54: =支払い明細!C55 -> 0 | J54: 資金複合 | N54: 対象外 | P54: =I54 -> 0 | Q54: =D54 -> （株）丸三
B55: =支払い明細!$E$1 -> 46042 | C55: 買掛金 | D55: =IF(IFERROR(VLOOKUP(支払い明細!B56,変換MAP!A:B,2,FALSE),"")=0,"",IFERROR(VLOOKUP(支払い明細!B56,変換MAP!A:B,2,FALSE),"")) -> 森川（株） | G55: 対象外 | I55: =支払い明細!C56 -> 444602 | J55: 資金複合 | N55: 対象外 | P55: =I55 -> 444602 | Q55: =D55 -> 森川（株）
B56: =支払い明細!$E$1 -> 46042 | C56: 買掛金 | D56: =IF(IFERROR(VLOOKUP(支払い明細!B57,変換MAP!A:B,2,FALSE),"")=0,"",IFERROR(VLOOKUP(支払い明細!B57,変換MAP!A:B,2,FALSE),"")) | G56: 対象外 | I56: =支払い明細!C57 -> 0 | J56: 資金複合 | N56: 対象外 | P56: =I56 -> 0
B57: =支払い明細!$E$1 -> 46042 | C57: 買掛金 | D57: =IF(IFERROR(VLOOKUP(支払い明細!B58,変換MAP!A:B,2,FALSE),"")=0,"",IFERROR(VLOOKUP(支払い明細!B58,変換MAP!A:B,2,FALSE),"")) | G57: 対象外 | I57: =支払い明細!C58 -> 0 | J57: 資金複合 | N57: 対象外 | P57: =I57 -> 0
B58: =支払い明細!$E$1 -> 46042 | C58: 買掛金 | D58: =IF(IFERROR(VLOOKUP(支払い明細!B59,変換MAP!A:B,2,FALSE),"")=0,"",IFERROR(VLOOKUP(支払い明細!B59,変換MAP!A:B,2,FALSE),"")) -> （株）よし与工房 | G58: 対象外 | I58: =支払い明細!C59 -> 0 | J58: 資金複合 | N58: 対象外 | P58: =I58 -> 0 | Q58: =D58 -> （株）よし与工房
B59: =支払い明細!$E$1 -> 46042 | D59: =IF(IFERROR(VLOOKUP(支払い明細!B60,変換MAP!A:B,2,FALSE),"")=0,"",IFERROR(VLOOKUP(支払い明細!B60,変換MAP!A:B,2,FALSE),"")) | G59: 対象外 | I59: =支払い明細!C60 -> 12159444 | P59: =I59 -> 12159444 | Q59: 本社仕入 合計
B60: =支払い明細!$E$1 -> 46042 | C60: 荷造運賃 | D60: =IF(IFERROR(VLOOKUP(支払い明細!B61,変換MAP!A:B,2,FALSE),"")=0,"",IFERROR(VLOOKUP(支払い明細!B61,変換MAP!A:B,2,FALSE),"")) | E60: 物販事業部 | G60: 課税仕入 10% | I60: =支払い明細!C61 -> 153087 | J60: 資金複合 | N60: 対象外 | P60: =I60 -> 153087 | Q60: 福山通運 | R60: 物販部 運賃
B61: =支払い明細!$E$1 -> 46042 | C61: 荷造運賃 | D61: =IF(IFERROR(VLOOKUP(支払い明細!B62,変換MAP!A:B,2,FALSE),"")=0,"",IFERROR(VLOOKUP(支払い明細!B62,変換MAP!A:B,2,FALSE),"")) | E61: 物販事業部 | G61: 課税仕入 10% | I61: =支払い明細!C62 -> 0 | J61: 資金複合 | N61: 対象外 | P61: =I61 -> 0 | Q61: 福山通運 第３事業部
B62: =支払い明細!$E$1 -> 46042 | C62: 荷造運賃 | D62: =IF(IFERROR(VLOOKUP(支払い明細!B63,変換MAP!A:B,2,FALSE),"")=0,"",IFERROR(VLOOKUP(支払い明細!B63,変換MAP!A:B,2,FALSE),"")) | E62: 物販事業部 | G62: 課税仕入 10% | I62: =支払い明細!C63 -> 203797 | J62: 資金複合 | N62: 対象外 | P62: =I62 -> 203797 | Q62: サクマ運輸㈱ | R62: 物販部 運賃
B63: =支払い明細!$E$1 -> 46042 | C63: 荷造運賃 | D63: =IF(IFERROR(VLOOKUP(支払い明細!B64,変換MAP!A:B,2,FALSE),"")=0,"",IFERROR(VLOOKUP(支払い明細!B64,変換MAP!A:B,2,FALSE),"")) | G63: 課税仕入 10% | I63: =支払い明細!C64 -> 128931 | J63: 資金複合 | N63: 対象外 | P63: =I63 -> 128931 | Q63: ティックトランスポート㈲ | R63: 物販部 運賃
B64: =支払い明細!$E$1 -> 46042 | C64: 仕入高 | D64: =IF(IFERROR(VLOOKUP(支払い明細!B65,変換MAP!A:B,2,FALSE),"")=0,"",IFERROR(VLOOKUP(支払い明細!B65,変換MAP!A:B,2,FALSE),"")) | G64: 課税仕入 10% | I64: =支払い明細!C65 -> 70400 | J64: 資金複合 | N64: 対象外 | P64: =I64 -> 70400 | Q64: ヨハネ印刷㈱ | R64: 物販部 仕入
B65: =支払い明細!$E$1 -> 46042 | C65: 消耗品費 | D65: =IF(IFERROR(VLOOKUP(支払い明細!B66,変換MAP!A:B,2,FALSE),"")=0,"",IFERROR(VLOOKUP(支払い明細!B66,変換MAP!A:B,2,FALSE),"")) | G65: 対象外 | I65: =支払い明細!C66 -> 18062 | J65: 資金複合 | N65: 対象外 | P65: =I65 -> 18062 | Q65: リコージャパン㈱ | R65: 物販部 事務用品費
B66: =支払い明細!$E$1 -> 46042 | C66: 車両費 | D66: =IF(IFERROR(VLOOKUP(支払い明細!B67,変換MAP!A:B,2,FALSE),"")=0,"",IFERROR(VLOOKUP(支払い明細!B67,変換MAP!A:B,2,FALSE),"")) | G66: 対象外 | I66: =支払い明細!C67 -> 540011 | J66: 資金複合 | N66: 対象外 | P66: =I66 -> 540011 | Q66: 広島トヨペット㈱ | R66: 車両費
B67: =支払い明細!$E$1 -> 46042 | C67: 仕入高 | D67: =IF(IFERROR(VLOOKUP(支払い明細!B68,変換MAP!A:B,2,FALSE),"")=0,"",IFERROR(VLOOKUP(支払い明細!B68,変換MAP!A:B,2,FALSE),"")) | G67: 課税仕入 10% | I67: =支払い明細!C68 -> 84810 | J67: 資金複合 | N67: 対象外 | P67: =I67 -> 84810 | Q67: ㈱ ナカガワ | R67: 物販部 仕入
B68: =支払い明細!$E$1 -> 46042 | C68: 仕入高 | D68: =IF(IFERROR(VLOOKUP(支払い明細!B69,変換MAP!A:B,2,FALSE),"")=0,"",IFERROR(VLOOKUP(支払い明細!B69,変換MAP!A:B,2,FALSE),"")) | G68: 課税仕入 10% | I68: =支払い明細!C69 -> 0 | J68: 資金複合 | N68: 対象外 | P68: =I68 -> 0 | Q68: 中国エンゼル㈱ | R68: 物販部 仕入
B69: =支払い明細!$E$1 -> 46042 | C69: 仕入高 | D69: =IF(IFERROR(VLOOKUP(支払い明細!B70,変換MAP!A:B,2,FALSE),"")=0,"",IFERROR(VLOOKUP(支払い明細!B70,変換MAP!A:B,2,FALSE),"")) | G69: 課税仕入 10% | I69: =支払い明細!C70 -> 0 | J69: 資金複合 | N69: 対象外 | P69: =I69 -> 0 | Q69: ㈱ ビバ
B70: =支払い明細!$E$1 -> 46042 | D70: =IF(IFERROR(VLOOKUP(支払い明細!B71,変換MAP!A:B,2,FALSE),"")=0,"",IFERROR(VLOOKUP(支払い明細!B71,変換MAP!A:B,2,FALSE),"")) | I70: =支払い明細!C71 -> 0 | P70: =I70 -> 0
B71: =支払い明細!$E$1 -> 46042 | D71: =IF(IFERROR(VLOOKUP(支払い明細!B72,変換MAP!A:B,2,FALSE),"")=0,"",IFERROR(VLOOKUP(支払い明細!B72,変換MAP!A:B,2,FALSE),"")) | I71: =支払い明細!C72 -> 1199098 | P71: =I71 -> 1199098 | Q71: その他小計
B72: =支払い明細!$E$1 -> 46042 | D72: =IF(IFERROR(VLOOKUP(支払い明細!B73,変換MAP!A:B,2,FALSE),"")=0,"",IFERROR(VLOOKUP(支払い明細!B73,変換MAP!A:B,2,FALSE),"")) | I72: =支払い明細!C73 -> 13358542 | P72: =I72 -> 13358542 | Q72: 合計の行 ここに振込手数料、早払いなどがある
B73: =支払い明細!$E$1 -> 46042 | D73: =IF(IFERROR(VLOOKUP(支払い明細!B74,変換MAP!A:B,2,FALSE),"")=0,"",IFERROR(VLOOKUP(支払い明細!B74,変換MAP!A:B,2,FALSE),"")) | I73: =支払い明細!C74 -> 0 | P73: =I73 -> 0
B74: =支払い明細!$E$1 -> 46042 | D74: =IF(IFERROR(VLOOKUP(支払い明細!B75,変換MAP!A:B,2,FALSE),"")=0,"",IFERROR(VLOOKUP(支払い明細!B75,変換MAP!A:B,2,FALSE),"")) | I74: =支払い明細!C75 -> 0 | P74: =I74 -> 0
B75: =支払い明細!$E$1 -> 46042 | D75: =IF(IFERROR(VLOOKUP(支払い明細!B76,変換MAP!A:B,2,FALSE),"")=0,"",IFERROR(VLOOKUP(支払い明細!B76,変換MAP!A:B,2,FALSE),"")) | I75: =支払い明細!C76 -> 0 | P75: =I75 -> 0
B76: =支払い明細!$E$1 -> 46042 | D76: =IF(IFERROR(VLOOKUP(支払い明細!B77,変換MAP!A:B,2,FALSE),"")=0,"",IFERROR(VLOOKUP(支払い明細!B77,変換MAP!A:B,2,FALSE),"")) | I76: =支払い明細!C77 -> 46042 | P76: =I76 -> 46042 | Q76: 20日払い振込手数料こちら持ち分の行 なので不要な行
B77: =支払い明細!$E$1 -> 46042 | D77: =IF(IFERROR(VLOOKUP(支払い明細!B78,変換MAP!A:B,2,FALSE),"")=0,"",IFERROR(VLOOKUP(支払い明細!B78,変換MAP!A:B,2,FALSE),"")) | I77: =支払い明細!C78 -> 請求額 | P77: =I77 -> 請求額
B78: =支払い明細!$E$1 -> 46042 | C78: 仕入高 | D78: =IF(IFERROR(VLOOKUP(支払い明細!B79,変換MAP!A:B,2,FALSE),"")=0,"",IFERROR(VLOOKUP(支払い明細!B79,変換MAP!A:B,2,FALSE),"")) | G78: 課税仕入 10% | I78: =支払い明細!C79 -> 11715 | J78: 資金複合 | N78: 対象外 | P78: =I78 -> 11715 | Q78: ワタキューセイモア㈱
B79: =支払い明細!$E$1 -> 46042 | C79: 仕入高 | D79: =IF(IFERROR(VLOOKUP(支払い明細!B80,変換MAP!A:B,2,FALSE),"")=0,"",IFERROR(VLOOKUP(支払い明細!B80,変換MAP!A:B,2,FALSE),"")) | G79: 課税仕入 10% | I79: =支払い明細!C80 -> 118426 | J79: 資金複合 | N79: 対象外 | P79: =I79 -> 118426 | Q79: ハウスホールドジャパン㈱
B80: =支払い明細!$E$1 -> 46042 | C80: 仕入高 | D80: =IF(IFERROR(VLOOKUP(支払い明細!B81,変換MAP!A:B,2,FALSE),"")=0,"",IFERROR(VLOOKUP(支払い明細!B81,変換MAP!A:B,2,FALSE),"")) | G80: 課税仕入 10% | I80: =支払い明細!C81 -> 0 | J80: 資金複合 | N80: 対象外 | P80: =I80 -> 0 | Q80: シンワ ㈱
B81: =支払い明細!$E$1 -> 46042 | C81: 仕入高 | D81: =IF(IFERROR(VLOOKUP(支払い明細!B82,変換MAP!A:B,2,FALSE),"")=0,"",IFERROR(VLOOKUP(支払い明細!B82,変換MAP!A:B,2,FALSE),"")) | G81: 課税仕入 10% | I81: =支払い明細!C82 -> 17820 | J81: 資金複合 | N81: 対象外 | P81: =I81 -> 17820 | Q81: ナカパック産業 ㈱
B82: =支払い明細!$E$1 -> 46042 | C82: 仕入高 | D82: =IF(IFERROR(VLOOKUP(支払い明細!B83,変換MAP!A:B,2,FALSE),"")=0,"",IFERROR(VLOOKUP(支払い明細!B83,変換MAP!A:B,2,FALSE),"")) -> （株）太幸 | G82: 課税仕入 10% | I82: =支払い明細!C83 -> 13915 | J82: 資金複合 | N82: 対象外 | P82: =I82 -> 13915 | Q82: ㈱ 太幸
B83: =支払い明細!$E$1 -> 46042 | C83: 仕入高 | D83: =IF(IFERROR(VLOOKUP(支払い明細!B84,変換MAP!A:B,2,FALSE),"")=0,"",IFERROR(VLOOKUP(支払い明細!B84,変換MAP!A:B,2,FALSE),"")) | G83: 課税仕入 10% | I83: =支払い明細!C84 -> 0 | J83: 資金複合 | N83: 対象外 | P83: =I83 -> 0 | Q83: ㈱ ユタカフードパック
B84: =支払い明細!$E$1 -> 46042 | C84: 仕入高 | D84: =IF(IFERROR(VLOOKUP(支払い明細!B85,変換MAP!A:B,2,FALSE),"")=0,"",IFERROR(VLOOKUP(支払い明細!B85,変換MAP!A:B,2,FALSE),"")) | G84: 課税仕入 10% | I84: =支払い明細!C85 -> 0 | J84: 資金複合 | N84: 対象外 | P84: =I84 -> 0 | Q84: 廣川 ㈱
B85: =支払い明細!$E$1 -> 46042 | C85: 仕入高 | D85: =IF(IFERROR(VLOOKUP(支払い明細!B86,変換MAP!A:B,2,FALSE),"")=0,"",IFERROR(VLOOKUP(支払い明細!B86,変換MAP!A:B,2,FALSE),"")) | G85: 課税仕入 10% | I85: =支払い明細!C86 -> 0 | J85: 資金複合 | N85: 対象外 | P85: =I85 -> 0 | Q85: ㈲ シルバー化成工業所
B86: =支払い明細!$E$1 -> 46042 | D86: =IF(IFERROR(VLOOKUP(支払い明細!B87,変換MAP!A:B,2,FALSE),"")=0,"",IFERROR(VLOOKUP(支払い明細!B87,変換MAP!A:B,2,FALSE),"")) | I86: =支払い明細!C87 -> 161876 | P86: =I86 -> 161876 | Q86: 小計の行
B87: =支払い明細!$E$1 -> 46042 | C87: 資金複合 | D87: =IF(IFERROR(VLOOKUP(支払い明細!B88,変換MAP!A:B,2,FALSE),"")=0,"",IFERROR(VLOOKUP(支払い明細!B88,変換MAP!A:B,2,FALSE),"")) | G87: 対象外 | I87: =支払い明細!F73 -> 20350 | J87: 仕入値引・戻し高 | L87: 物販事業部 | N87: 課税仕入-返還等 10% | P87: =I87 -> 20350 | Q87: 振込手数料値引／20日払い分
B88: =支払い明細!$E$1 -> 46042 | C88: 資金複合 | G88: 対象外 | I88: =支払い明細!H73 -> 60836 | J88: 早払収益 | L88: 物販事業部 | N88: 非課税売上 | P88: =I88 -> 60836 | Q88: 早払収益／20日払い分

Sheet 変換MAP
A1: EXCEL | B1: MF
A2: イトマン ㈱ | B2: イトマン（株）
A3: 泉 製紙 ㈱ | B3: 泉製紙（株）
A4: オルディ 株式会社 | B4: オルディ株式会社
A5: 木野川紙業 株式会社 | B5: 木野川紙業（株）
A6: ケイティケイ ㈱ | B6: ｋｔｋ ケイティケイ（株）
A7: ㈱ 尚美堂 | B7: （株）尚美堂
A8: シーバイエス ㈱ | B8: シーバイエス（株）
A9: ㈱ スズカ未来 | B9: （株）スズカ未来
A10: 中国鉄管継手㈱
A11: ツバメ工業
A12: ㈱ 奈良半商店
A13: 中川製袋化工 ㈱ | B13: 中川製袋化工（株）
A14: 広島共和物産㈱ | B14: 広島共和物産（株）
A15: 福助工業㈱ | B15: 福助工業（株）
A16: ㈱ やしき | B16: （株）やしき
A17: ユニ・チャーム ㈱ | B17: ユニ・チャーム(株)
A18: 旭創業 ㈱ | B18: （株）旭創業
A19: ㈱ アルファ
A20: ㈱ 大阪包装社 | B20: （株）大阪包装社
A21: カミイソ産商 ㈱ | B21: カミイソ産商（株）
A22: 木村アルミ箔 ㈱ | B22: 木村アルミ箔（株）
A23: 酒井美化工業 ㈱
A24: ㈱ ササガワ
A25: ㈱ 四国フソウ
A26: 信和 ㈱
A27: ㈱ セイコー | B27: （株）セイコー
A28: ㈱ 太幸 | B28: （株）太幸
A29: 大黒工業㈱ | B29: 大黒工業（株）
A30: ㈱ パックタケヤマ | B30: （株）パックタケヤマ
A31: ㈲ タイヨー
A32: ㈱ ちどり産業
A33: シーピー化成 ㈱ | B33: シービー化成（株）
A34: カネカ食品販売 ㈱
A35: ㈱ 中国リス食品販売
A36: 天満紙器 株式会社 | B36: 天満紙器（株）
A37: 東光 株式会社 | B37: （株）東光
A38: ㈲ 東予割箸
A39: ㈲ トックブランシュ
A40: ナカパック産業 ㈱
A41: ㈱ 中村製紙所
A42: ㈱ ニューパック住友
A43: ㈱ ﾊﾗﾌﾟﾚｯｸｽ松山支店 | B43: （株）ハラプレックス
A44: 広川 ㈱
A45: ㈱ フォーデック
A46: ㈱ 福重
A47: ㈱ プライム.ハラ
A48: ㈱ 藤井包材
A49: ㈱ ベルベ
A50: ホリアキ 株式会社 | B50: ホリアキ（株）
A51: 信越ファインテック ㈱ | B51: 信越ファインテック（株）
A52: ㈱ 丸三 | B52: （株）丸三
A53: 森川 ㈱ | B53: 森川（株）
A54: 八家化学工業 ㈱
A55: ㈱ ユタカフードパック
A56: ㈱ よし与工房 | B56: （株）よし与工房
